XTTOOLS/CommonError.py
XTTOOLS/CommonResponse.py
XTTOOLS/__init__.py
XTTOOLS/cache.py
XTTOOLS/encrypt.py
XTTOOLS/filterbuilder.py
XTTOOLS/snowFlakeId.py
XTTOOLS/xtjson.py
XTTOOLS-1.3.dist-info/LICENSE
XTTOOLS-1.3.dist-info/METADATA
XTTOOLS-1.3.dist-info/WHEEL
XTTOOLS-1.3.dist-info/top_level.txt
XTTOOLS-1.3.dist-info/RECORD
