Metadata-Version: 2.1
Name: XTTOOLS
Version: 1.3
Summary: XTJsonResponse
Home-page: https://github.com/fengchuan1021
Author: fengchuan
Author-email: fengchuanhn@gmail.com
Classifier: Programming Language :: Python :: 3
Classifier: License :: OSI Approved :: MIT License
Classifier: Operating System :: OS Independent
License-File: LICENSE
Requires-Dist: sqlalchemy
Requires-Dist: pydantic
Requires-Dist: orjson
